ribopy/__init__.py
ribopy/_version.py
ribopy/create.py
ribopy/dump.py
ribopy/info.py
ribopy/merge.py
ribopy/metadata.py
ribopy/plot.py
ribopy/rnaseq.py
ribopy/settings.py
ribopy/api/__init__.py
ribopy/api/alias.py
ribopy/api/api_helpers.py
ribopy/api/get_transcript_coverage.py
ribopy/api/ribo.py
ribopy/cli/__init__.py
ribopy/cli/create.py
ribopy/cli/dump.py
ribopy/cli/info.py
ribopy/cli/main.py
ribopy/cli/merge.py
ribopy/cli/metadata.py
ribopy/cli/plot.py
ribopy/cli/rnaseq.py
ribopy/core/__init__.py
ribopy/core/aggregate_by_length.py
ribopy/core/coverage.py
ribopy/core/create_experiment.py
ribopy/core/exceptions.py
ribopy/core/get_gadgets.py
ribopy/core/metagene.py
ribopy/core/quantify.py
ribopy/core/region_counts.py
ribopy/core/verify.py
ribopy/core/write_profile.py
ribopy/io/__init__.py
ribopy/io/dump_coverage.py
ribopy/io/file.py
ribopy/io/metadata.py
ribopy/io/read_line_chunks.py
ribopy/io/separate_by_length.py
ribopy/io/write_profile.py
tests/__init__.py
tests/annotation_test_data.py
tests/multilength_test_data.py
tests/rnaseq_data.py
tests/test_data.py
ribopy-0.0.1.dist-info/LICENSE
ribopy-0.0.1.dist-info/METADATA
ribopy-0.0.1.dist-info/WHEEL
ribopy-0.0.1.dist-info/entry_points.txt
ribopy-0.0.1.dist-info/top_level.txt
ribopy-0.0.1.dist-info/RECORD
