Metadata-Version: 2.1
Name: ribopy
Version: 0.0.1
Summary: Tools for creating and reading Ribo files.
Home-page: UNKNOWN
Author: Hakan Ozadam
License: MIT
Platform: UNKNOWN
Classifier: Development Status :: 2 - Pre-Alpha
Classifier: Operating System :: OS Independent
Classifier: Programming Language :: Python
Classifier: Programming Language :: Python :: 3
Classifier: Programming Language :: Python :: 3.6
Classifier: Programming Language :: Python :: 3.7
